main.py
ciris_adapters/README.md
ciris_adapters/__init__.py
ciris_adapters/ciris_covenant_metrics/README.md
ciris_adapters/ciris_covenant_metrics/__init__.py
ciris_adapters/ciris_covenant_metrics/adapter.py
ciris_adapters/ciris_covenant_metrics/manifest.json
ciris_adapters/ciris_covenant_metrics/services.py
ciris_adapters/ciris_hosted_tools/__init__.py
ciris_adapters/ciris_hosted_tools/adapter.py
ciris_adapters/ciris_hosted_tools/manifest.json
ciris_adapters/ciris_hosted_tools/services.py
ciris_adapters/external_data_sql/README.md
ciris_adapters/external_data_sql/__init__.py
ciris_adapters/external_data_sql/adapter.py
ciris_adapters/external_data_sql/configurable.py
ciris_adapters/external_data_sql/example_config.json
ciris_adapters/external_data_sql/example_privacy_schema.yaml
ciris_adapters/external_data_sql/manifest.json
ciris_adapters/external_data_sql/privacy_schema_loader.py
ciris_adapters/external_data_sql/protocol.py
ciris_adapters/external_data_sql/schemas.py
ciris_adapters/external_data_sql/service.py
ciris_adapters/external_data_sql/service_old.py
ciris_adapters/external_data_sql/dialects/__init__.py
ciris_adapters/external_data_sql/dialects/base.py
ciris_adapters/external_data_sql/dialects/mysql.py
ciris_adapters/external_data_sql/dialects/postgresql.py
ciris_adapters/external_data_sql/dialects/sqlite.py
ciris_adapters/home_assistant/__init__.py
ciris_adapters/home_assistant/adapter.py
ciris_adapters/home_assistant/communication_service.py
ciris_adapters/home_assistant/configurable.py
ciris_adapters/home_assistant/manifest.json
ciris_adapters/home_assistant/schemas.py
ciris_adapters/home_assistant/service.py
ciris_adapters/home_assistant/tool_service.py
ciris_adapters/mcp_client/__init__.py
ciris_adapters/mcp_client/adapter.py
ciris_adapters/mcp_client/config.py
ciris_adapters/mcp_client/configurable.py
ciris_adapters/mcp_client/manifest.json
ciris_adapters/mcp_client/mcp_communication_service.py
ciris_adapters/mcp_client/mcp_tool_service.py
ciris_agent-1.7.9.dist-info/licenses/LICENSE
ciris_agent-1.7.9.dist-info/licenses/NOTICE
ciris_agent-1.7.9.dist-info/METADATA
ciris_agent-1.7.9.dist-info/WHEEL
ciris_agent-1.7.9.dist-info/entry_points.txt
ciris_agent-1.7.9.dist-info/top_level.txt
ciris_agent-1.7.9.dist-info/RECORD
