Metadata-Version: 2.4
Name: ciris-agent
Version: 1.7.9
Summary: CIRIS: Ethical AI Agent with Consensual Evolution Protocol
Home-page: https://github.com/CIRISAI/CIRISAgent
Author: Eric Moore
Author-email: eric@ciris.ai
Project-URL: Bug Reports, https://github.com/CIRISAI/CIRISAgent/issues
Project-URL: Source, https://github.com/CIRISAI/CIRISAgent
Project-URL: Documentation, https://github.com/CIRISAI/CIRISAgent/tree/main/docs
Keywords: ai agent ethical-ai autonomous-agent discord-bot api-server
Classifier: Development Status :: 4 - Beta
Classifier: Intended Audience :: Developers
Classifier: Intended Audience :: Science/Research
Classifier: License :: OSI Approved :: Apache Software License
Classifier: Programming Language :: Python :: 3
Classifier: Programming Language :: Python :: 3.10
Classifier: Programming Language :: Python :: 3.11
Classifier: Programming Language :: Python :: 3.12
Classifier: Topic :: Scientific/Engineering :: Artificial Intelligence
Classifier: Topic :: Software Development :: Libraries :: Application Frameworks
Requires-Python: >=3.10
License-File: LICENSE
License-File: NOTICE
Requires-Dist: pydantic<3.0.0,>=2.7.0
Requires-Dist: openai<2.0.0,>=1.0.0
Requires-Dist: instructor<2.0.0,>=1.11.3
Requires-Dist: PyYAML<7.0.0,>=6.0.1
Requires-Dist: psycopg2-binary<3.0.0,>=2.9.0
Requires-Dist: SQLAlchemy<3.0.0,>=2.0.0
Requires-Dist: aiohttp<4.0.0,>=3.9.0
Requires-Dist: httpx<1.0.0,>=0.25.0
Requires-Dist: anyio<5.0.0,>=4.0.0
Requires-Dist: discord.py<3.0.0,>=2.3.0
Requires-Dist: pypdf<7.0.0,>=6.0.0
Requires-Dist: docx2txt<1.0.0,>=0.8
Requires-Dist: cryptography<46.0.0,>=41.0.0
Requires-Dist: PyJWT[crypto]<3.0.0,>=2.8.0
Requires-Dist: bcrypt<5.0.0,>=4.0.0
Requires-Dist: PyNaCl<2.0.0,>=1.5.0
Requires-Dist: fastapi<1.0.0,>=0.111.0
Requires-Dist: uvicorn[standard]<1.0.0,>=0.29.0
Requires-Dist: websockets>=14.0
Requires-Dist: python-multipart<1.0.0,>=0.0.6
Requires-Dist: aiofiles<24.0.0,>=23.2.0
Requires-Dist: python-dotenv<2.0.0,>=1.0.0
Requires-Dist: networkx<4.0,>=3.0
Requires-Dist: psutil<6.0.0,>=5.9.0
Requires-Dist: croniter<3.0.0,>=2.0.0
Requires-Dist: backoff<3.0.0,>=2.2.0
Requires-Dist: zeroconf<1.0.0,>=0.39.0
Requires-Dist: click<9.0.0,>=8.1.0
Requires-Dist: docker<8.0.0,>=6.0.0
Provides-Extra: dev
Requires-Dist: pytest<8.0.0,>=7.4.0; extra == "dev"
Requires-Dist: pytest-asyncio<1.0.0,>=0.21.0; extra == "dev"
Requires-Dist: pytest-cov<5.0.0,>=4.1.0; extra == "dev"
Requires-Dist: pytest-timeout<3.0.0,>=2.2.0; extra == "dev"
Requires-Dist: pytest-xdist<4.0.0,>=3.3.0; extra == "dev"
Requires-Dist: pytest-rerunfailures<17.0.0,>=16.0.0; extra == "dev"
Requires-Dist: pytest-mock<4.0.0,>=3.12.0; extra == "dev"
Requires-Dist: hypothesis<7.0.0,>=6.0.0; extra == "dev"
Requires-Dist: mypy<2.0.0,>=1.8.0; extra == "dev"
Requires-Dist: types-psutil<6.0.0,>=5.9.0; extra == "dev"
Requires-Dist: types-PyYAML<7.0.0,>=6.0.0; extra == "dev"
Requires-Dist: types-aiofiles<24.0.0,>=23.0.0; extra == "dev"
Requires-Dist: instructor<2.0.0,>=1.11.3; extra == "dev"
Requires-Dist: astunparse<2.0.0,>=1.6.3; extra == "dev"
Requires-Dist: websocket-client<2.0.0,>=1.6.0; extra == "dev"
Requires-Dist: zeroconf<1.0.0,>=0.39.0; extra == "dev"
Dynamic: author
Dynamic: author-email
Dynamic: classifier
Dynamic: description
Dynamic: description-content-type
Dynamic: home-page
Dynamic: keywords
Dynamic: license-file
Dynamic: project-url
Dynamic: provides-extra
Dynamic: requires-dist
Dynamic: requires-python
Dynamic: summary
